usermail_converter/UI.py
usermail_converter/__init__.py
usermail_converter/__main__.py
usermail_converter/converters.py
usermail_converter/icons/icon256.ico
usermail_converter/icons/icon256.png
usermail_converter-1.1.dist-info/LICENSE
usermail_converter-1.1.dist-info/METADATA
usermail_converter-1.1.dist-info/WHEEL
usermail_converter-1.1.dist-info/entry_points.txt
usermail_converter-1.1.dist-info/top_level.txt
usermail_converter-1.1.dist-info/RECORD
