Metadata-Version: 2.1
Name: usermail-converter
Version: 1.1
Summary: A Python Cross Platform GUI App Tool to Convert Between Emails and Usernames
Home-page: https://github.com/ThamiMemel/UserMail_Converter
Author: Thami Memel
Author-email: memelthami@gmail.com
License: GPLv3
Download-URL: https://github.com/ThamiMemel/usermail-converter/archive/1.1.tar.gz
Keywords: username,email,mail,converter,combo
Platform: UNKNOWN
Classifier: Development Status :: 5 - Production/Stable
Classifier: Intended Audience :: End Users/Desktop
Classifier: Topic :: Software Development :: Build Tools
Classifier: License :: OSI Approved :: GNU General Public License v3 (GPLv3)
Classifier: Topic :: Utilities
Classifier: Natural Language :: English
Classifier: Operating System :: POSIX :: Linux
Classifier: Operating System :: MacOS
Classifier: Operating System :: Microsoft :: Windows
Classifier: Programming Language :: Python :: 3
Classifier: Programming Language :: Python :: 3.5
Classifier: Programming Language :: Python :: 3.6
Classifier: Programming Language :: Python :: 3.7
Classifier: Programming Language :: Python :: 3.8
Requires-Dist: pyqt5 (==5.14.2)
Requires-Dist: PyAutoGUI (==0.9.50)
